graphiti_core/__init__.py
graphiti_core/edges.py
graphiti_core/errors.py
graphiti_core/graph_queries.py
graphiti_core/graphiti.py
graphiti_core/graphiti_types.py
graphiti_core/helpers.py
graphiti_core/nodes.py
graphiti_core/py.typed
graphiti_core/cross_encoder/__init__.py
graphiti_core/cross_encoder/bge_reranker_client.py
graphiti_core/cross_encoder/client.py
graphiti_core/cross_encoder/gemini_reranker_client.py
graphiti_core/cross_encoder/openai_reranker_client.py
graphiti_core/driver/__init__.py
graphiti_core/driver/driver.py
graphiti_core/driver/falkordb_driver.py
graphiti_core/driver/neo4j_driver.py
graphiti_core/embedder/__init__.py
graphiti_core/embedder/azure_openai.py
graphiti_core/embedder/client.py
graphiti_core/embedder/gemini.py
graphiti_core/embedder/openai.py
graphiti_core/embedder/voyage.py
graphiti_core/llm_client/__init__.py
graphiti_core/llm_client/anthropic_client.py
graphiti_core/llm_client/azure_openai_client.py
graphiti_core/llm_client/client.py
graphiti_core/llm_client/config.py
graphiti_core/llm_client/errors.py
graphiti_core/llm_client/gemini_client.py
graphiti_core/llm_client/groq_client.py
graphiti_core/llm_client/openai_base_client.py
graphiti_core/llm_client/openai_client.py
graphiti_core/llm_client/openai_generic_client.py
graphiti_core/llm_client/utils.py
graphiti_core/models/__init__.py
graphiti_core/models/edges/__init__.py
graphiti_core/models/edges/edge_db_queries.py
graphiti_core/models/nodes/__init__.py
graphiti_core/models/nodes/node_db_queries.py
graphiti_core/prompts/__init__.py
graphiti_core/prompts/dedupe_edges.py
graphiti_core/prompts/dedupe_nodes.py
graphiti_core/prompts/eval.py
graphiti_core/prompts/extract_edge_dates.py
graphiti_core/prompts/extract_edges.py
graphiti_core/prompts/extract_nodes.py
graphiti_core/prompts/invalidate_edges.py
graphiti_core/prompts/lib.py
graphiti_core/prompts/models.py
graphiti_core/prompts/prompt_helpers.py
graphiti_core/prompts/summarize_nodes.py
graphiti_core/search/__init__.py
mseep_graphiti_core-0.17.6.dist-info/licenses/LICENSE
mseep_graphiti_core-0.17.6.dist-info/METADATA
mseep_graphiti_core-0.17.6.dist-info/WHEEL
mseep_graphiti_core-0.17.6.dist-info/top_level.txt
mseep_graphiti_core-0.17.6.dist-info/RECORD
