Metadata-Version: 2.4
Name: mseep-graphiti-core
Version: 0.17.6
Summary: A temporal graph building library
Home-page: https://github.com/mseep
Author: mseep
Author-email: support@skydeck.ai
Maintainer: mseep
Maintainer-email: support@skydeck.ai
Keywords: mseep
Classifier: Programming Language :: Python :: 3
Classifier: License :: OSI Approved :: MIT License
Classifier: Operating System :: OS Independent
Requires-Python: >=3.6
License-File: LICENSE
Requires-Dist: pydantic>=2.11.5
Requires-Dist: neo4j>=5.26.0
Requires-Dist: diskcache>=5.6.3
Requires-Dist: openai>=1.91.0
Requires-Dist: tenacity>=9.0.0
Requires-Dist: numpy>=1.0.0
Requires-Dist: python-dotenv>=1.0.1
Requires-Dist: posthog>=3.0.0
Dynamic: author
Dynamic: author-email
Dynamic: classifier
Dynamic: description
Dynamic: description-content-type
Dynamic: home-page
Dynamic: keywords
Dynamic: license-file
Dynamic: maintainer
Dynamic: maintainer-email
Dynamic: requires-dist
Dynamic: requires-python
Dynamic: summary
